gitlab_job_exporter/__init__.py
gitlab_job_exporter-0.0.9.data/scripts/gitlab_job_exporter
gitlab_job_exporter-0.0.9.dist-info/METADATA
gitlab_job_exporter-0.0.9.dist-info/WHEEL
gitlab_job_exporter-0.0.9.dist-info/top_level.txt
gitlab_job_exporter-0.0.9.dist-info/RECORD
