Metadata-Version: 2.1
Name: gitlab-job-exporter
Version: 0.0.9
Summary: Package to scrape running_time, duration_time, status, etc. of Gitlab jobs using prometheus time series format
Home-page: https://gitlab.codecentric.de/cloudcentric/openstack-gitlab-runner
Author: Sven Hertzberg
Author-email: sven.hertzberg@codecentric.cloud
License: MIT
Platform: UNKNOWN
Requires-Dist: prometheus-client
Requires-Dist: python-dateutil
Requires-Dist: urllib3
Requires-Dist: requests
